tc1d/__init__.py
tc1d/tc1d.py
tc1d/tc1d_cli.py
tc1d/madtrax/__init__.py
tc1d/madtrax/madtrax_apatite.py
tc1d/madtrax/madtrax_zircon.py
tc1d/melts_data/dryBasalt.csv
tc1d/melts_data/dryFelsic.csv
tc1d/melts_data/wetBasalt2.csv
tc1d/melts_data/wetFelsic4.csv
tc1d/melts_data/wetImed3.csv
tc1d-0.3.2.dist-info/METADATA
tc1d-0.3.2.dist-info/WHEEL
tc1d-0.3.2.dist-info/entry_points.txt
tc1d-0.3.2.dist-info/licenses/LICENSE
tc1d-0.3.2.dist-info/RECORD
