Metadata-Version: 2.4
Name: tc1d
Version: 0.3.2
Summary: A 1D thermal model and thermochronometer age prediction code
Project-URL: homepage, https://tc1d.readthedocs.io/
Project-URL: repository, https://github.com/HUGG/TC1D
Project-URL: documentation, https://tc1d.readthedocs.io/
Author-email: Dave Whipp <david.whipp@helsinki.fi>, Benjamin Gérard <benjamin.gerard@helsinki.fi>, Sanni Laaksonen <sanni.laaksonen@helsinki.fi>
License:                     GNU GENERAL PUBLIC LICENSE
License-File: LICENSE
Keywords: geology,geophysics,heat transfer,thermochronology
Classifier: Development Status :: 4 - Beta
Classifier: Intended Audience :: Developers
Classifier: Intended Audience :: Science/Research
Classifier: License :: OSI Approved :: GNU General Public License v3 or later (GPLv3+)
Classifier: Natural Language :: English
Classifier: Operating System :: OS Independent
Classifier: Programming Language :: Python :: 3
Classifier: Programming Language :: Python :: 3 :: Only
Classifier: Programming Language :: Python :: 3.10
Classifier: Programming Language :: Python :: 3.11
Classifier: Programming Language :: Python :: 3.12
Classifier: Programming Language :: Python :: 3.13
Classifier: Topic :: Scientific/Engineering
Classifier: Topic :: Scientific/Engineering :: Physics
Requires-Python: >=3.10.0
Requires-Dist: corner
Requires-Dist: emcee
Requires-Dist: matplotlib
Requires-Dist: mpi4py
Requires-Dist: neighpy
Requires-Dist: numpy
Requires-Dist: openmpi
Requires-Dist: schwimmbad
Requires-Dist: scikit-learn
Requires-Dist: scipy
Provides-Extra: lint
Requires-Dist: mypy; extra == 'lint'
Requires-Dist: ruff; extra == 'lint'
Provides-Extra: notebook
Requires-Dist: jupyterlab; extra == 'notebook'
Provides-Extra: tests
Requires-Dist: mpi4py; extra == 'tests'
Requires-Dist: openmpi; extra == 'tests'
Requires-Dist: pytest; extra == 'tests'
